dtt_common/__init__.py
dtt_common/common_class.py
dtt_common/common_logger.py
dtt_common-0.2.3.dist-info/METADATA
dtt_common-0.2.3.dist-info/WHEEL
dtt_common-0.2.3.dist-info/top_level.txt
dtt_common-0.2.3.dist-info/RECORD
