Metadata-Version: 2.1
Name: dtt-common
Version: 0.2.3
Requires-Dist: selenium >=4.0
Requires-Dist: pytest >=7.4.2
Requires-Dist: imutils >=0.5
Requires-Dist: opencv-python >=4.8.0.0
Requires-Dist: scikit-image >=0.21.0
